pyokofen/__init__.py
pyokofen/okofen.py
pyokofen/utils.py
PyOkofen-1.0.1.dist-info/LICENSE
PyOkofen-1.0.1.dist-info/METADATA
PyOkofen-1.0.1.dist-info/WHEEL
PyOkofen-1.0.1.dist-info/top_level.txt
PyOkofen-1.0.1.dist-info/RECORD
